NuRadioMC/EvtGen/.gitignore
NuRadioMC/EvtGen/NuRadioMCtoAraSim.py
NuRadioMC/EvtGen/NuRadioProposal.py
NuRadioMC/EvtGen/README
NuRadioMC/EvtGen/__init__.py
NuRadioMC/EvtGen/config_PROPOSAL.json
NuRadioMC/EvtGen/config_PROPOSAL_greenland.json
NuRadioMC/EvtGen/config_PROPOSAL_infice.json
NuRadioMC/EvtGen/config_PROPOSAL_mooresbay.json
NuRadioMC/EvtGen/create_tau_tab.py
NuRadioMC/EvtGen/decay_library.hdf5
NuRadioMC/EvtGen/generate_cylinder.py
NuRadioMC/EvtGen/generate_unforced.py
NuRadioMC/EvtGen/generator.py
NuRadioMC/EvtGen/generator_ASCII.py
NuRadioMC/EvtGen/generator_skeleton.py
NuRadioMC/EvtGen/hdf5_to_ASCII.py
NuRadioMC/EvtGen/proposal_table_manager.py
NuRadioMC/EvtGen/readARAEventList.py
NuRadioMC/EvtGen/readEventList_ASCII.py
NuRadioMC/EvtGen/tests/T01test_additional_interactions.py
NuRadioMC/EvtGen/tests/T02_create_tau_dataset.py
NuRadioMC/EvtGen/tests/T03_tau_length.py
NuRadioMC/EvtGen/tests/T07_read_tab.py
NuRadioMC/EvtGen/tests/T08_tau_PROPOSAL.py
NuRadioMC/EvtGen/tests/T09_plot_PROPOSAL_diff.py
NuRadioMC/SignalGen/ARZ/.gitignore
NuRadioMC/SignalGen/ARZ/ARZ.py
NuRadioMC/SignalGen/ARZ/__init__.py
NuRadioMC/SignalGen/ARZ/scripts/A01preprocess_shower_library.py
NuRadioMC/SignalGen/ARZ/scripts/A01preprocess_shower_library_v1.2.py
NuRadioMC/SignalGen/ARZ/scripts/A02plot_library_stats.py
NuRadioMC/SignalGen/ARZ/scripts/B01create_pulse_library.py
NuRadioMC/SignalGen/ARZ/scripts/B02create_pulse_library_per_energy.py
NuRadioMC/SignalGen/ARZ/scripts/fortran_reference.dat
NuRadioMC/SignalGen/ARZ/shower_library/.gitignore
NuRadioMC/SignalGen/ARZ/shower_library/nue_1EeV_CC_1_s0001.t1005
NuRadioMC/SignalGen/ARZ/shower_library/nue_1EeV_CC_1_s0001.t1006
NuRadioMC/SignalGen/ARZ/shower_library/shower_lib_hash.json
NuRadioMC/SignalGen/ARZ/tests/T01CompareWithFast.py
NuRadioMC/SignalGen/ARZ/tests/T02TestARZ.py
NuRadioMC/SignalGen/ARZ/tests/T03TestSpeedup.py
NuRadioMC/SignalGen/ARZ/tests/T04InterpolationFactors.py
NuRadioMC/SignalGen/ARZ/tests/T05PlotInterp.py
nuradiomc-3.1.0.dist-info/METADATA
nuradiomc-3.1.0.dist-info/WHEEL
nuradiomc-3.1.0.dist-info/licenses/LICENSE
nuradiomc-3.1.0.dist-info/RECORD
