Metadata-Version: 2.4
Name: NuRadioMC
Version: 3.1.0
Summary: A Monte Carlo simulation package for radio neutrino detectors and reconstruction framework for radio detectors of high-energy neutrinos and cosmic-rays.
License: GPL-3.0-or-later
License-File: LICENSE
Author: Christian Glaser et al.
Requires-Python: >=3.7,<4.0
Classifier: License :: OSI Approved :: GNU General Public License v3 or later (GPLv3+)
Classifier: Programming Language :: Python :: 3
Classifier: Programming Language :: Python :: 3.7
Classifier: Programming Language :: Python :: 3.8
Classifier: Programming Language :: Python :: 3.9
Classifier: Programming Language :: Python :: 3.10
Classifier: Programming Language :: Python :: 3.11
Classifier: Programming Language :: Python :: 3.12
Classifier: Programming Language :: Python :: 3.13
Classifier: Programming Language :: Python :: 3.14
Provides-Extra: all
Provides-Extra: cr-interpolator
Provides-Extra: dev
Provides-Extra: galacticnoise
Provides-Extra: muon-flux
Provides-Extra: proposal
Requires-Dist: MCEq ; extra == "muon-flux" or extra == "all"
Requires-Dist: Sphinx ; extra == "dev"
Requires-Dist: aenum
Requires-Dist: astropy
Requires-Dist: awkward
Requires-Dist: cr-pulse-interpolator (>=1.1.1) ; extra == "cr-interpolator" or extra == "all"
Requires-Dist: crflux ; extra == "muon-flux" or extra == "all"
Requires-Dist: cython
Requires-Dist: dash (>=2.0)
Requires-Dist: filelock
Requires-Dist: future
Requires-Dist: h5py
Requires-Dist: healpy ; extra == "galacticnoise" or extra == "all"
Requires-Dist: importlib-metadata (>=4.8.1) ; python_version < "3.8"
Requires-Dist: matplotlib
Requires-Dist: numba
Requires-Dist: numpy
Requires-Dist: numpydoc ; extra == "dev"
Requires-Dist: peakutils
Requires-Dist: pre-commit ; extra == "dev"
Requires-Dist: proposal (==7.6.2) ; extra == "proposal" or extra == "all"
Requires-Dist: pygdsm ; extra == "galacticnoise"
Requires-Dist: pylfmap ; extra == "galacticnoise" or extra == "all"
Requires-Dist: pymongo
Requires-Dist: pyyaml
Requires-Dist: radiotools (>=0.2.1)
Requires-Dist: requests
Requires-Dist: scipy
Requires-Dist: sphinx-rtd-theme ; extra == "dev"
Requires-Dist: tinydb (>=4.1.1)
Requires-Dist: tinydb-serialization (>=2.1)
Requires-Dist: toml (>=0.10.2)
Requires-Dist: uproot
Project-URL: Documentation, https://nu-radio.github.io/NuRadioMC/main.html
Project-URL: Homepage, https://github.com/nu-radio/NuRadioMC
